[
    {
        "image": "https://static.wixstatic.com/media/9c6671_f5cbab3b21a240bfa896655c281f7938~mv2.jpeg/v1/fill/w_980,h_496,al_c,q_85,usm_0.66_1.00_0.01,enc_auto/9c6671_f5cbab3b21a240bfa896655c281f7938~mv2.jpeg",
        "title": "1. Elevated Living ",
        "para": "A \"playground of well-being\" nestled in the heart of the Himalayas, Dunagiri Retreat is devoted entirely to wellbeing. The campus offers a vast array of accommodations, yoga halls, meditation rooms, and experiences, such as hikes, yoga, sound healing, wilderness exploration, and more."
    },
    {
        "image": "https://static.wixstatic.com/media/9c6671_494b2f709514485b8004b95fb66652ed~mv2.jpg/v1/fill/w_1092,h_559,al_c,q_85,usm_0.66_1.00_0.01,enc_auto/9c6671_494b2f709514485b8004b95fb66652ed~mv2.jpg",
        "title": "2. Yoga & Meditation Near Babaji's Cave",
        "para": "Retreat leaders and participants get access to our main Yoga Hall, which can host up to 40 people, our Pyramid Meditation Hall, a capacity of 20 people, and Babaji Temple, a capacity of 20 people."
    },
    {
        "image": "https://static.wixstatic.com/media/9c6671_8e2794c148c149879d1ae7c411f4c54e.jpg/v1/fill/w_1092,h_605,al_c,q_85,usm_0.66_1.00_0.01,enc_auto/9c6671_8e2794c148c149879d1ae7c411f4c54e.jpg",
        "title": "3. Farm-Fresh Ayurvedic Meals",
        "para": "Nourish your body with clean, locally sourced vegan meals developed by our local Chef. Our light and savory meals are included (at no extra charge) with each stay and are specially designed using Ayurvedic principles to support the multi-step detoxification process so you can leave feeling better than ever."
    }
]